setup.py
src/impaf_beaker.egg-info/PKG-INFO
src/impaf_beaker.egg-info/SOURCES.txt
src/impaf_beaker.egg-info/dependency_links.txt
src/impaf_beaker.egg-info/namespace_packages.txt
src/impaf_beaker.egg-info/not-zip-safe
src/impaf_beaker.egg-info/requires.txt
src/impaf_beaker.egg-info/top_level.txt
src/implugin/__init__.py
src/implugin/beaker.py
src/implugin/test_beaker.py